src/__init__.py
src/foldup/__init__.py
src/foldup/cli.py
src/foldup/core.py
src/foldup/defaults.py
src/foldup/utils.py
foldup-0.1.1.dist-info/METADATA
foldup-0.1.1.dist-info/WHEEL
foldup-0.1.1.dist-info/entry_points.txt
foldup-0.1.1.dist-info/licenses/LICENSE
foldup-0.1.1.dist-info/RECORD
