Metadata-Version: 2.4
Name: foldup
Version: 0.1.1
Summary: Fold your codebase into a single Markdown file for passing to an LLM.
Project-URL: Homepage, https://github.com/nathanclairmonte/foldup
Project-URL: Issues, https://github.com/nathanclairmonte/foldup/issues
License-Expression: MIT
License-File: LICENSE
Classifier: Operating System :: OS Independent
Classifier: Programming Language :: Python :: 3
Requires-Python: >=3.9
Requires-Dist: click>=8.1.7
Requires-Dist: pathspec>=0.12.1
Requires-Dist: pyyaml>=6.0.2
Requires-Dist: tiktoken>=0.8.0
